{
  "generated_at": "2026-06-30T12:22:51.056001+00:00",
  "source": "OSM Overpass + Nominatim + Wikidata + Railway + Maritime + FIRMS modules",
  "version": "coordinate-intelligence-v7-firms",
  "status": "ok",
  "note": "This is rule-based OSINT assistance, not confirmed target identification.",
  "coordinate": {
    "lat": 45.336521,
    "lon": 36.46503
  },
  "search_radius_m": 750,
  "primary_radius_m": 75,
  "secondary_radius_m": 150,
  "location": {
    "status": "ok",
    "country": "Україна",
    "country_code": "ua",
    "region": "Автономна Республіка Крим",
    "county": "Керченський район",
    "city": "Керчь",
    "locality": null,
    "road": "Таманская улица",
    "nearest_named_place": "Таманская улица",
    "display_name": "Таманская улица, Керчь, Керченський район, Автономна Республіка Крим, 298320, Україна"
  },
  "summary": {
    "likely_object": "Port-linked energy / refinery infrastructure",
    "confidence": "HIGH",
    "primary_object": "Port infrastructure",
    "primary_confidence": "HIGH",
    "operational_environment": "Rail logistics area",
    "environment_confidence": "HIGH",
    "environment_score": 690.4,
    "fusion_reason": "Port infrastructure is combined with fuel, storage or industrial indicators.",
    "country": "Україна",
    "region": "Автономна Республіка Крим",
    "nearest_city": "Керчь",
    "nearest_locality": null,
    "nearest_road": "Таманская улица",
    "nearest_named_place": "Таманская улица",
    "nearest_wikidata": "Kerch",
    "feature_counts": {
      "port": 20,
      "railway": 126,
      "road": 93,
      "storage": 28,
      "industrial": 6,
      "warehouse": 2,
      "fuel": 2,
      "military": 1
    },
    "strong_feature_count": 278,
    "weak_feature_count": 3007,
    "railway_confidence": "HIGH",
    "maritime_confidence": "HIGH",
    "firms_activity_detected": false,
    "firms_activity_window": "30d",
    "firms_activity_count": 0,
    "firms_nearest_hotspot_m": null,
    "firms_confidence": "LOW",
    "firms_latest_detection": null
  },
  "primary_object": {
    "type": "Port infrastructure",
    "feature_type": "port",
    "confidence": "HIGH",
    "score": 56.0,
    "reason": "Primary object inferred from mapped features within 75 m.",
    "evidence": [
      {
        "osm_id": 264298404,
        "osm_type": "way",
        "name": "Pier / berth",
        "raw_name": "Unnamed object",
        "feature_type": "port",
        "evidence_strength": "strong",
        "weight": 11.2,
        "distance_m": 44.6,
        "lat": 45.336919,
        "lon": 36.465109,
        "tags": {
          "man_made": "pier"
        }
      },
      {
        "osm_id": 264298423,
        "osm_type": "way",
        "name": "Pier / berth",
        "raw_name": "Unnamed object",
        "feature_type": "port",
        "evidence_strength": "strong",
        "weight": 11.2,
        "distance_m": 54.8,
        "lat": 45.337009,
        "lon": 36.465122,
        "tags": {
          "man_made": "pier"
        }
      },
      {
        "osm_id": 264298396,
        "osm_type": "way",
        "name": "Pier / berth",
        "raw_name": "Unnamed object",
        "feature_type": "port",
        "evidence_strength": "strong",
        "weight": 11.2,
        "distance_m": 59.0,
        "lat": 45.336395,
        "lon": 36.464297,
        "tags": {
          "man_made": "pier"
        }
      },
      {
        "osm_id": 264298401,
        "osm_type": "way",
        "name": "Pier / berth",
        "raw_name": "Unnamed object",
        "feature_type": "port",
        "evidence_strength": "strong",
        "weight": 11.2,
        "distance_m": 69.6,
        "lat": 45.337142,
        "lon": 36.465135,
        "tags": {
          "man_made": "pier"
        }
      },
      {
        "osm_id": 264298403,
        "osm_type": "way",
        "name": "Pier / berth",
        "raw_name": "Unnamed object",
        "feature_type": "port",
        "evidence_strength": "strong",
        "weight": 11.2,
        "distance_m": 75.0,
        "lat": 45.33672,
        "lon": 36.464112,
        "tags": {
          "man_made": "pier"
        }
      }
    ]
  },
  "operational_environment": {
    "type": "Rail logistics area",
    "confidence": "HIGH",
    "score": 690.4,
    "reason": "Strong feature types: 8. Nearby strong features within 500 m: 148.",
    "score_breakdown": {
      "Commercial port / logistics hub": 676.71,
      "Airfield / airbase area": 4.64,
      "Fuel or storage facility": 334.02,
      "Rail logistics area": 690.4,
      "Bridge / transport crossing environment": 421.33,
      "Military-related area": 49.56,
      "Industrial area": 74.39
    },
    "feature_counts": {
      "other": 3007,
      "port": 20,
      "railway": 126,
      "road": 93,
      "storage": 28,
      "industrial": 6,
      "warehouse": 2,
      "fuel": 2,
      "military": 1
    }
  },
  "fusion_profile": {
    "type": "Port-linked energy / refinery infrastructure",
    "confidence": "HIGH",
    "reason": "Port infrastructure is combined with fuel, storage or industrial indicators."
  },
  "nominatim": {
    "status": "ok",
    "source": "Nominatim / OpenStreetMap",
    "display_name": "Таманская улица, Керчь, Керченський район, Автономна Республіка Крим, 298320, Україна",
    "osm_type": "way",
    "osm_id": 106448121,
    "category": "highway",
    "type": "residential",
    "name": "Таманская улица",
    "address": {
      "country": "Україна",
      "country_code": "ua",
      "region": "Автономна Республіка Крим",
      "county": "Керченський район",
      "city": "Керчь",
      "locality": null,
      "road": "Таманская улица"
    },
    "extratags": {
      "surface": "asphalt"
    },
    "namedetails": {
      "name": "Таманская улица",
      "name:ru": "Таманская улица",
      "name:uk": "Таманська вулиця"
    }
  },
  "wikidata": {
    "status": "ok",
    "source": "Wikidata SPARQL",
    "radius_m": 750,
    "count": 10,
    "candidates": [
      {
        "id": "Q157065",
        "url": "http://www.wikidata.org/entity/Q157065",
        "name": "Kerch",
        "type": "big city",
        "distance_km": 0.332,
        "distance_m": 331.6,
        "lat": 45.338611,
        "lon": 36.468056
      },
      {
        "id": "Q157065",
        "url": "http://www.wikidata.org/entity/Q157065",
        "name": "Kerch",
        "type": "municipal formation in Russia",
        "distance_km": 0.332,
        "distance_m": 331.6,
        "lat": 45.338611,
        "lon": 36.468056
      },
      {
        "id": "Q157065",
        "url": "http://www.wikidata.org/entity/Q157065",
        "name": "Kerch",
        "type": "city or town",
        "distance_km": 0.332,
        "distance_m": 331.6,
        "lat": 45.338611,
        "lon": 36.468056
      },
      {
        "id": "Q157065",
        "url": "http://www.wikidata.org/entity/Q157065",
        "name": "Kerch",
        "type": "city in Ukraine",
        "distance_km": 0.332,
        "distance_m": 331.6,
        "lat": 45.338611,
        "lon": 36.468056
      },
      {
        "id": "Q906661",
        "url": "http://www.wikidata.org/entity/Q906661",
        "name": "Panticapaeum",
        "type": "polis",
        "distance_km": 0.332,
        "distance_m": 331.6,
        "lat": 45.338611,
        "lon": 36.468056
      },
      {
        "id": "Q906661",
        "url": "http://www.wikidata.org/entity/Q906661",
        "name": "Panticapaeum",
        "type": "archaeological site",
        "distance_km": 0.332,
        "distance_m": 331.6,
        "lat": 45.338611,
        "lon": 36.468056
      },
      {
        "id": "Q16533315",
        "url": "http://www.wikidata.org/entity/Q16533315",
        "name": "Q16533315",
        "type": null,
        "distance_km": 0.332,
        "distance_m": 331.6,
        "lat": 45.338611,
        "lon": 36.468056
      },
      {
        "id": "Q4336060",
        "url": "http://www.wikidata.org/entity/Q4336060",
        "name": "Орджоникидзевский район",
        "type": "raion of city in Ukraine",
        "distance_km": 0.371,
        "distance_m": 370.7,
        "lat": 45.33441,
        "lon": 36.46136
      },
      {
        "id": "Q4336060",
        "url": "http://www.wikidata.org/entity/Q4336060",
        "name": "Орджоникидзевский район",
        "type": "city district in Russia",
        "distance_km": 0.371,
        "distance_m": 370.7,
        "lat": 45.33441,
        "lon": 36.46136
      },
      {
        "id": "Q14812992",
        "url": "http://www.wikidata.org/entity/Q14812992",
        "name": "Kerch Fishing Port",
        "type": "port",
        "distance_km": 0.419,
        "distance_m": 419.3,
        "lat": 45.3383,
        "lon": 36.4603
      }
    ],
    "nearest": {
      "id": "Q157065",
      "url": "http://www.wikidata.org/entity/Q157065",
      "name": "Kerch",
      "type": "big city",
      "distance_km": 0.332,
      "distance_m": 331.6,
      "lat": 45.338611,
      "lon": 36.468056
    }
  },
  "railway": {
    "status": "ok",
    "source": "OSM Railway Intelligence",
    "rail_present": true,
    "rail_count": 126,
    "nearest_track_m": 81.3,
    "bridge_count": 0,
    "warehouse_count": 2,
    "industrial_count": 6,
    "logistics_score": 640,
    "confidence": "HIGH",
    "nearest_features": [
      {
        "osm_id": 1058360573,
        "osm_type": "way",
        "name": "Крымская железная дорога",
        "raw_name": "Крымская железная дорога",
        "feature_type": "railway",
        "evidence_strength": "strong",
        "weight": 5.75,
        "distance_m": 81.3,
        "lat": 45.335792,
        "lon": 36.464962,
        "tags": {
          "branch": "КРЫМ",
          "electrified": "no",
          "gauge": "1520",
          "operator": "Крымская железная дорога",
          "railway": "rail",
          "service": "siding",
          "source": "Bing"
        }
      },
      {
        "osm_id": 1058360574,
        "osm_type": "way",
        "name": "Крымская железная дорога",
        "raw_name": "Крымская железная дорога",
        "feature_type": "railway",
        "evidence_strength": "strong",
        "weight": 5.75,
        "distance_m": 109.4,
        "lat": 45.335537,
        "lon": 36.465029,
        "tags": {
          "branch": "КРЫМ",
          "electrified": "no",
          "gauge": "1520",
          "operator": "Крымская железная дорога",
          "railway": "rail",
          "service": "siding",
          "source": "Bing"
        }
      },
      {
        "osm_id": 1058360575,
        "osm_type": "way",
        "name": "Крымская железная дорога",
        "raw_name": "Крымская железная дорога",
        "feature_type": "railway",
        "evidence_strength": "strong",
        "weight": 5.75,
        "distance_m": 111.9,
        "lat": 45.335526,
        "lon": 36.464816,
        "tags": {
          "branch": "КРЫМ",
          "electrified": "no",
          "gauge": "1520",
          "operator": "Крымская железная дорога",
          "railway": "rail",
          "service": "siding",
          "source": "Bing"
        }
      },
      {
        "osm_id": 239059741,
        "osm_type": "way",
        "name": "Крымская железная дорога",
        "raw_name": "Крымская железная дорога",
        "feature_type": "railway",
        "evidence_strength": "strong",
        "weight": 5.75,
        "distance_m": 129.5,
        "lat": 45.335357,
        "lon": 36.464984,
        "tags": {
          "branch": "КРЫМ",
          "electrified": "no",
          "gauge": "1520",
          "operator": "Крымская железная дорога",
          "railway": "rail",
          "service": "siding",
          "source": "Bing"
        }
      },
      {
        "osm_id": 239059743,
        "osm_type": "way",
        "name": "Крымская железная дорога",
        "raw_name": "Крымская железная дорога",
        "feature_type": "railway",
        "evidence_strength": "strong",
        "weight": 4.0,
        "distance_m": 153.7,
        "lat": 45.335138,
        "lon": 36.465043,
        "tags": {
          "branch": "КРЫМ",
          "electrified": "no",
          "gauge": "1520",
          "operator": "Крымская железная дорога",
          "railway": "rail",
          "service": "siding",
          "source": "Bing"
        }
      },
      {
        "osm_id": 239058833,
        "osm_type": "way",
        "name": "Крымская железная дорога",
        "raw_name": "Крымская железная дорога",
        "feature_type": "railway",
        "evidence_strength": "strong",
        "weight": 4.0,
        "distance_m": 162.3,
        "lat": 45.336163,
        "lon": 36.467043,
        "tags": {
          "branch": "КРЫМ",
          "electrified": "no",
          "gauge": "1520",
          "operator": "Крымская железная дорога",
          "railway": "rail",
          "service": "siding",
          "source": "Bing"
        }
      },
      {
        "osm_id": 239058836,
        "osm_type": "way",
        "name": "Крымская железная дорога",
        "raw_name": "Крымская железная дорога",
        "feature_type": "railway",
        "evidence_strength": "strong",
        "weight": 4.0,
        "distance_m": 195.2,
        "lat": 45.336849,
        "lon": 36.467483,
        "tags": {
          "branch": "КРЫМ",
          "electrified": "no",
          "gauge": "1520",
          "operator": "Крымская железная дорога",
          "railway": "rail",
          "service": "siding",
          "source": "Bing"
        }
      },
      {
        "osm_id": 2468726589,
        "osm_type": "node",
        "name": "Railway segment",
        "raw_name": "Unnamed object",
        "feature_type": "railway",
        "evidence_strength": "strong",
        "weight": 4.0,
        "distance_m": 226.0,
        "lat": 45.335194,
        "lon": 36.46722,
        "tags": {
          "railway": "level_crossing"
        }
      },
      {
        "osm_id": 2468726592,
        "osm_type": "node",
        "name": "Railway segment",
        "raw_name": "Unnamed object",
        "feature_type": "railway",
        "evidence_strength": "strong",
        "weight": 4.0,
        "distance_m": 231.2,
        "lat": 45.335192,
        "lon": 36.467304,
        "tags": {
          "railway": "level_crossing"
        }
      },
      {
        "osm_id": 239059740,
        "osm_type": "way",
        "name": "Крымская железная дорога",
        "raw_name": "Крымская железная дорога",
        "feature_type": "railway",
        "evidence_strength": "strong",
        "weight": 4.0,
        "distance_m": 284.0,
        "lat": 45.333991,
        "lon": 36.464537,
        "tags": {
          "branch": "КРЫМ",
          "electrified": "no",
          "gauge": "1520",
          "operator": "Крымская железная дорога",
          "railway": "rail",
          "service": "siding",
          "source": "Bing"
        }
      }
    ]
  },
  "maritime": {
    "status": "ok",
    "source": "OSM Maritime Intelligence",
    "port_present": true,
    "port_count": 20,
    "pier_count": 19,
    "quay_count": 0,
    "breakwater_count": 0,
    "ferry_terminal_count": 1,
    "harbour_count": 0,
    "nearest_port_m": 44.6,
    "railway_support_count": 126,
    "storage_support_count": 28,
    "fuel_support_count": 2,
    "industrial_support_count": 6,
    "maritime_score": 329,
    "confidence": "HIGH",
    "profile": "Port with rail-connected logistics infrastructure",
    "nearest_features": [
      {
        "osm_id": 264298404,
        "osm_type": "way",
        "name": "Pier / berth",
        "raw_name": "Unnamed object",
        "feature_type": "port",
        "evidence_strength": "strong",
        "weight": 11.2,
        "distance_m": 44.6,
        "lat": 45.336919,
        "lon": 36.465109,
        "tags": {
          "man_made": "pier"
        }
      },
      {
        "osm_id": 264298423,
        "osm_type": "way",
        "name": "Pier / berth",
        "raw_name": "Unnamed object",
        "feature_type": "port",
        "evidence_strength": "strong",
        "weight": 11.2,
        "distance_m": 54.8,
        "lat": 45.337009,
        "lon": 36.465122,
        "tags": {
          "man_made": "pier"
        }
      },
      {
        "osm_id": 264298396,
        "osm_type": "way",
        "name": "Pier / berth",
        "raw_name": "Unnamed object",
        "feature_type": "port",
        "evidence_strength": "strong",
        "weight": 11.2,
        "distance_m": 59.0,
        "lat": 45.336395,
        "lon": 36.464297,
        "tags": {
          "man_made": "pier"
        }
      },
      {
        "osm_id": 264298401,
        "osm_type": "way",
        "name": "Pier / berth",
        "raw_name": "Unnamed object",
        "feature_type": "port",
        "evidence_strength": "strong",
        "weight": 11.2,
        "distance_m": 69.6,
        "lat": 45.337142,
        "lon": 36.465135,
        "tags": {
          "man_made": "pier"
        }
      },
      {
        "osm_id": 264298403,
        "osm_type": "way",
        "name": "Pier / berth",
        "raw_name": "Unnamed object",
        "feature_type": "port",
        "evidence_strength": "strong",
        "weight": 11.2,
        "distance_m": 75.0,
        "lat": 45.33672,
        "lon": 36.464112,
        "tags": {
          "man_made": "pier"
        }
      },
      {
        "osm_id": 264298419,
        "osm_type": "way",
        "name": "Pier / berth",
        "raw_name": "Unnamed object",
        "feature_type": "port",
        "evidence_strength": "strong",
        "weight": 8.05,
        "distance_m": 75.6,
        "lat": 45.336867,
        "lon": 36.464197,
        "tags": {
          "man_made": "pier"
        }
      },
      {
        "osm_id": 264298395,
        "osm_type": "way",
        "name": "Pier / berth",
        "raw_name": "Unnamed object",
        "feature_type": "port",
        "evidence_strength": "strong",
        "weight": 8.05,
        "distance_m": 77.2,
        "lat": 45.336514,
        "lon": 36.464043,
        "tags": {
          "man_made": "pier"
        }
      },
      {
        "osm_id": 264298422,
        "osm_type": "way",
        "name": "Pier / berth",
        "raw_name": "Unnamed object",
        "feature_type": "port",
        "evidence_strength": "strong",
        "weight": 8.05,
        "distance_m": 77.9,
        "lat": 45.336572,
        "lon": 36.464036,
        "tags": {
          "man_made": "pier"
        }
      },
      {
        "osm_id": 264298433,
        "osm_type": "way",
        "name": "Pier / berth",
        "raw_name": "Unnamed object",
        "feature_type": "port",
        "evidence_strength": "strong",
        "weight": 8.05,
        "distance_m": 78.5,
        "lat": 45.336415,
        "lon": 36.464038,
        "tags": {
          "man_made": "pier"
        }
      },
      {
        "osm_id": 264298391,
        "osm_type": "way",
        "name": "Pier / berth",
        "raw_name": "Unnamed object",
        "feature_type": "port",
        "evidence_strength": "strong",
        "weight": 8.05,
        "distance_m": 82.5,
        "lat": 45.336316,
        "lon": 36.464016,
        "tags": {
          "man_made": "pier"
        }
      }
    ]
  },
  "firms": {
    "status": "ok",
    "source": "NASA FIRMS local repository files",
    "radius_m": 750,
    "activity_detected": false,
    "activity_window": "30d",
    "activity_count": 0,
    "nearest_hotspot_m": null,
    "max_frp": null,
    "latest_detection": null,
    "confidence": "LOW",
    "assessment": "No FIRMS thermal anomaly was detected within 750 m in the available local FIRMS windows.",
    "windows": {
      "24h": {
        "window": "24h",
        "source_path": "data/firms_1.json",
        "status": "ok",
        "radius_m": 750,
        "hotspot_count": 0,
        "nearest_hotspot_m": null,
        "max_frp": null,
        "latest_detection": null,
        "confidence": "LOW",
        "hotspots": []
      },
      "72h": {
        "window": "72h",
        "source_path": "data/firms_3.json",
        "status": "ok",
        "radius_m": 750,
        "hotspot_count": 0,
        "nearest_hotspot_m": null,
        "max_frp": null,
        "latest_detection": null,
        "confidence": "LOW",
        "hotspots": []
      },
      "10d": {
        "window": "10d",
        "source_path": "data/firms_10.json",
        "status": "ok",
        "radius_m": 750,
        "hotspot_count": 0,
        "nearest_hotspot_m": null,
        "max_frp": null,
        "latest_detection": null,
        "confidence": "LOW",
        "hotspots": []
      },
      "30d": {
        "window": "30d",
        "source_path": "data/firms_30.json",
        "status": "ok",
        "radius_m": 750,
        "hotspot_count": 0,
        "nearest_hotspot_m": null,
        "max_frp": null,
        "latest_detection": null,
        "confidence": "LOW",
        "hotspots": []
      }
    }
  },
  "evidence_features": [
    {
      "osm_id": 264298404,
      "osm_type": "way",
      "name": "Pier / berth",
      "raw_name": "Unnamed object",
      "feature_type": "port",
      "evidence_strength": "strong",
      "weight": 11.2,
      "distance_m": 44.6,
      "lat": 45.336919,
      "lon": 36.465109,
      "tags": {
        "man_made": "pier"
      }
    },
    {
      "osm_id": 264298423,
      "osm_type": "way",
      "name": "Pier / berth",
      "raw_name": "Unnamed object",
      "feature_type": "port",
      "evidence_strength": "strong",
      "weight": 11.2,
      "distance_m": 54.8,
      "lat": 45.337009,
      "lon": 36.465122,
      "tags": {
        "man_made": "pier"
      }
    },
    {
      "osm_id": 264298396,
      "osm_type": "way",
      "name": "Pier / berth",
      "raw_name": "Unnamed object",
      "feature_type": "port",
      "evidence_strength": "strong",
      "weight": 11.2,
      "distance_m": 59.0,
      "lat": 45.336395,
      "lon": 36.464297,
      "tags": {
        "man_made": "pier"
      }
    },
    {
      "osm_id": 264298401,
      "osm_type": "way",
      "name": "Pier / berth",
      "raw_name": "Unnamed object",
      "feature_type": "port",
      "evidence_strength": "strong",
      "weight": 11.2,
      "distance_m": 69.6,
      "lat": 45.337142,
      "lon": 36.465135,
      "tags": {
        "man_made": "pier"
      }
    },
    {
      "osm_id": 264298403,
      "osm_type": "way",
      "name": "Pier / berth",
      "raw_name": "Unnamed object",
      "feature_type": "port",
      "evidence_strength": "strong",
      "weight": 11.2,
      "distance_m": 75.0,
      "lat": 45.33672,
      "lon": 36.464112,
      "tags": {
        "man_made": "pier"
      }
    },
    {
      "osm_id": 264298419,
      "osm_type": "way",
      "name": "Pier / berth",
      "raw_name": "Unnamed object",
      "feature_type": "port",
      "evidence_strength": "strong",
      "weight": 8.05,
      "distance_m": 75.6,
      "lat": 45.336867,
      "lon": 36.464197,
      "tags": {
        "man_made": "pier"
      }
    },
    {
      "osm_id": 264298395,
      "osm_type": "way",
      "name": "Pier / berth",
      "raw_name": "Unnamed object",
      "feature_type": "port",
      "evidence_strength": "strong",
      "weight": 8.05,
      "distance_m": 77.2,
      "lat": 45.336514,
      "lon": 36.464043,
      "tags": {
        "man_made": "pier"
      }
    },
    {
      "osm_id": 264298422,
      "osm_type": "way",
      "name": "Pier / berth",
      "raw_name": "Unnamed object",
      "feature_type": "port",
      "evidence_strength": "strong",
      "weight": 8.05,
      "distance_m": 77.9,
      "lat": 45.336572,
      "lon": 36.464036,
      "tags": {
        "man_made": "pier"
      }
    },
    {
      "osm_id": 264298433,
      "osm_type": "way",
      "name": "Pier / berth",
      "raw_name": "Unnamed object",
      "feature_type": "port",
      "evidence_strength": "strong",
      "weight": 8.05,
      "distance_m": 78.5,
      "lat": 45.336415,
      "lon": 36.464038,
      "tags": {
        "man_made": "pier"
      }
    },
    {
      "osm_id": 1058360573,
      "osm_type": "way",
      "name": "Крымская железная дорога",
      "raw_name": "Крымская железная дорога",
      "feature_type": "railway",
      "evidence_strength": "strong",
      "weight": 5.75,
      "distance_m": 81.3,
      "lat": 45.335792,
      "lon": 36.464962,
      "tags": {
        "branch": "КРЫМ",
        "electrified": "no",
        "gauge": "1520",
        "operator": "Крымская железная дорога",
        "railway": "rail",
        "service": "siding",
        "source": "Bing"
      }
    },
    {
      "osm_id": 264298391,
      "osm_type": "way",
      "name": "Pier / berth",
      "raw_name": "Unnamed object",
      "feature_type": "port",
      "evidence_strength": "strong",
      "weight": 8.05,
      "distance_m": 82.5,
      "lat": 45.336316,
      "lon": 36.464016,
      "tags": {
        "man_made": "pier"
      }
    },
    {
      "osm_id": 264298424,
      "osm_type": "way",
      "name": "Pier / berth",
      "raw_name": "Unnamed object",
      "feature_type": "port",
      "evidence_strength": "strong",
      "weight": 8.05,
      "distance_m": 84.4,
      "lat": 45.337275,
      "lon": 36.465146,
      "tags": {
        "man_made": "pier"
      }
    },
    {
      "osm_id": 264298430,
      "osm_type": "way",
      "name": "Pier / berth",
      "raw_name": "Unnamed object",
      "feature_type": "port",
      "evidence_strength": "strong",
      "weight": 8.05,
      "distance_m": 85.4,
      "lat": 45.336258,
      "lon": 36.464004,
      "tags": {
        "man_made": "pier"
      }
    },
    {
      "osm_id": 264298402,
      "osm_type": "way",
      "name": "Pier / berth",
      "raw_name": "Unnamed object",
      "feature_type": "port",
      "evidence_strength": "strong",
      "weight": 8.05,
      "distance_m": 90.4,
      "lat": 45.336098,
      "lon": 36.464042,
      "tags": {
        "man_made": "pier"
      }
    },
    {
      "osm_id": 264298416,
      "osm_type": "way",
      "name": "Pier / berth",
      "raw_name": "Unnamed object",
      "feature_type": "port",
      "evidence_strength": "strong",
      "weight": 8.05,
      "distance_m": 97.8,
      "lat": 45.335936,
      "lon": 36.464096,
      "tags": {
        "man_made": "pier"
      }
    },
    {
      "osm_id": 264298392,
      "osm_type": "way",
      "name": "Pier / berth",
      "raw_name": "Unnamed object",
      "feature_type": "port",
      "evidence_strength": "strong",
      "weight": 8.05,
      "distance_m": 104.1,
      "lat": 45.337453,
      "lon": 36.465164,
      "tags": {
        "man_made": "pier"
      }
    },
    {
      "osm_id": 1058360574,
      "osm_type": "way",
      "name": "Крымская железная дорога",
      "raw_name": "Крымская железная дорога",
      "feature_type": "railway",
      "evidence_strength": "strong",
      "weight": 5.75,
      "distance_m": 109.4,
      "lat": 45.335537,
      "lon": 36.465029,
      "tags": {
        "branch": "КРЫМ",
        "electrified": "no",
        "gauge": "1520",
        "operator": "Крымская железная дорога",
        "railway": "rail",
        "service": "siding",
        "source": "Bing"
      }
    },
    {
      "osm_id": 1058360575,
      "osm_type": "way",
      "name": "Крымская железная дорога",
      "raw_name": "Крымская железная дорога",
      "feature_type": "railway",
      "evidence_strength": "strong",
      "weight": 5.75,
      "distance_m": 111.9,
      "lat": 45.335526,
      "lon": 36.464816,
      "tags": {
        "branch": "КРЫМ",
        "electrified": "no",
        "gauge": "1520",
        "operator": "Крымская железная дорога",
        "railway": "rail",
        "service": "siding",
        "source": "Bing"
      }
    },
    {
      "osm_id": 264298420,
      "osm_type": "way",
      "name": "Pier / berth",
      "raw_name": "Unnamed object",
      "feature_type": "port",
      "evidence_strength": "strong",
      "weight": 8.05,
      "distance_m": 123.9,
      "lat": 45.33763,
      "lon": 36.465187,
      "tags": {
        "man_made": "pier"
      }
    },
    {
      "osm_id": 239059741,
      "osm_type": "way",
      "name": "Крымская железная дорога",
      "raw_name": "Крымская железная дорога",
      "feature_type": "railway",
      "evidence_strength": "strong",
      "weight": 5.75,
      "distance_m": 129.5,
      "lat": 45.335357,
      "lon": 36.464984,
      "tags": {
        "branch": "КРЫМ",
        "electrified": "no",
        "gauge": "1520",
        "operator": "Крымская железная дорога",
        "railway": "rail",
        "service": "siding",
        "source": "Bing"
      }
    },
    {
      "osm_id": 264298436,
      "osm_type": "way",
      "name": "Pier / berth",
      "raw_name": "Unnamed object",
      "feature_type": "port",
      "evidence_strength": "strong",
      "weight": 8.05,
      "distance_m": 136.5,
      "lat": 45.33562,
      "lon": 36.463844,
      "tags": {
        "man_made": "pier"
      }
    },
    {
      "osm_id": 239059743,
      "osm_type": "way",
      "name": "Крымская железная дорога",
      "raw_name": "Крымская железная дорога",
      "feature_type": "railway",
      "evidence_strength": "strong",
      "weight": 4.0,
      "distance_m": 153.7,
      "lat": 45.335138,
      "lon": 36.465043,
      "tags": {
        "branch": "КРЫМ",
        "electrified": "no",
        "gauge": "1520",
        "operator": "Крымская железная дорога",
        "railway": "rail",
        "service": "siding",
        "source": "Bing"
      }
    },
    {
      "osm_id": 239058833,
      "osm_type": "way",
      "name": "Крымская железная дорога",
      "raw_name": "Крымская железная дорога",
      "feature_type": "railway",
      "evidence_strength": "strong",
      "weight": 4.0,
      "distance_m": 162.3,
      "lat": 45.336163,
      "lon": 36.467043,
      "tags": {
        "branch": "КРЫМ",
        "electrified": "no",
        "gauge": "1520",
        "operator": "Крымская железная дорога",
        "railway": "rail",
        "service": "siding",
        "source": "Bing"
      }
    },
    {
      "osm_id": 264298387,
      "osm_type": "way",
      "name": "Pier / berth",
      "raw_name": "Unnamed object",
      "feature_type": "port",
      "evidence_strength": "strong",
      "weight": 5.6,
      "distance_m": 177.1,
      "lat": 45.335394,
      "lon": 36.463428,
      "tags": {
        "man_made": "pier"
      }
    },
    {
      "osm_id": 574181777,
      "osm_type": "way",
      "name": "Road segment",
      "raw_name": "Unnamed object",
      "feature_type": "road",
      "evidence_strength": "strong",
      "weight": 2.4,
      "distance_m": 188.7,
      "lat": 45.335241,
      "lon": 36.466614,
      "tags": {
        "highway": "service"
      }
    }
  ],
  "weak_features": [
    {
      "osm_id": 28006961,
      "osm_type": "node",
      "name": "Unclassified mapped object",
      "raw_name": "Unnamed object",
      "feature_type": "other",
      "evidence_strength": "weak",
      "weight": 0.0,
      "distance_m": 7.7,
      "lat": 45.33659,
      "lon": 36.465045,
      "tags": {}
    },
    {
      "osm_id": 9725199825,
      "osm_type": "node",
      "name": "Unclassified mapped object",
      "raw_name": "Unnamed object",
      "feature_type": "other",
      "evidence_strength": "weak",
      "weight": 0.0,
      "distance_m": 11.6,
      "lat": 45.33652,
      "lon": 36.464881,
      "tags": {}
    },
    {
      "osm_id": 9725199826,
      "osm_type": "node",
      "name": "Unclassified mapped object",
      "raw_name": "Unnamed object",
      "feature_type": "other",
      "evidence_strength": "weak",
      "weight": 0.0,
      "distance_m": 19.9,
      "lat": 45.336543,
      "lon": 36.464778,
      "tags": {}
    },
    {
      "osm_id": 2468736928,
      "osm_type": "node",
      "name": "Unclassified mapped object",
      "raw_name": "Unnamed object",
      "feature_type": "other",
      "evidence_strength": "weak",
      "weight": 0.0,
      "distance_m": 29.4,
      "lat": 45.336774,
      "lon": 36.465141,
      "tags": {}
    },
    {
      "osm_id": 9725199215,
      "osm_type": "node",
      "name": "Unclassified mapped object",
      "raw_name": "Unnamed object",
      "feature_type": "other",
      "evidence_strength": "weak",
      "weight": 0.0,
      "distance_m": 29.7,
      "lat": 45.336787,
      "lon": 36.465058,
      "tags": {}
    },
    {
      "osm_id": 9725199216,
      "osm_type": "node",
      "name": "Unclassified mapped object",
      "raw_name": "Unnamed object",
      "feature_type": "other",
      "evidence_strength": "weak",
      "weight": 0.0,
      "distance_m": 31.2,
      "lat": 45.336775,
      "lon": 36.465198,
      "tags": {}
    },
    {
      "osm_id": 5512201571,
      "osm_type": "node",
      "name": "Unclassified mapped object",
      "raw_name": "Unnamed object",
      "feature_type": "other",
      "evidence_strength": "weak",
      "weight": 0.0,
      "distance_m": 32.3,
      "lat": 45.336618,
      "lon": 36.464641,
      "tags": {}
    },
    {
      "osm_id": 2468736926,
      "osm_type": "node",
      "name": "Unclassified mapped object",
      "raw_name": "Unnamed object",
      "feature_type": "other",
      "evidence_strength": "weak",
      "weight": 0.0,
      "distance_m": 34.3,
      "lat": 45.336789,
      "lon": 36.465246,
      "tags": {}
    },
    {
      "osm_id": 1879085566,
      "osm_type": "node",
      "name": "Unclassified mapped object",
      "raw_name": "Unnamed object",
      "feature_type": "other",
      "evidence_strength": "weak",
      "weight": 0.0,
      "distance_m": 36.6,
      "lat": 45.336848,
      "lon": 36.465082,
      "tags": {}
    },
    {
      "osm_id": 2699878611,
      "osm_type": "node",
      "name": "Unclassified mapped object",
      "raw_name": "Unnamed object",
      "feature_type": "other",
      "evidence_strength": "weak",
      "weight": 0.0,
      "distance_m": 36.6,
      "lat": 45.336846,
      "lon": 36.465103,
      "tags": {}
    },
    {
      "osm_id": 2699878588,
      "osm_type": "node",
      "name": "Unclassified mapped object",
      "raw_name": "Unnamed object",
      "feature_type": "other",
      "evidence_strength": "weak",
      "weight": 0.0,
      "distance_m": 38.5,
      "lat": 45.336248,
      "lon": 36.464727,
      "tags": {}
    },
    {
      "osm_id": 2699878596,
      "osm_type": "node",
      "name": "Unclassified mapped object",
      "raw_name": "Unnamed object",
      "feature_type": "other",
      "evidence_strength": "weak",
      "weight": 0.0,
      "distance_m": 43.1,
      "lat": 45.336384,
      "lon": 36.464515,
      "tags": {}
    },
    {
      "osm_id": 1879085565,
      "osm_type": "node",
      "name": "Unclassified mapped object",
      "raw_name": "Unnamed object",
      "feature_type": "other",
      "evidence_strength": "weak",
      "weight": 0.0,
      "distance_m": 43.8,
      "lat": 45.336409,
      "lon": 36.464493,
      "tags": {}
    },
    {
      "osm_id": 27933627,
      "osm_type": "node",
      "name": "Unclassified mapped object",
      "raw_name": "Unnamed object",
      "feature_type": "other",
      "evidence_strength": "weak",
      "weight": 0.0,
      "distance_m": 45.5,
      "lat": 45.336823,
      "lon": 36.465424,
      "tags": {}
    },
    {
      "osm_id": 264298335,
      "osm_type": "way",
      "name": "Unclassified mapped object",
      "raw_name": "Unnamed object",
      "feature_type": "other",
      "evidence_strength": "weak",
      "weight": 0.0,
      "distance_m": 46.5,
      "lat": 45.336206,
      "lon": 36.464638,
      "tags": {
        "building": "yes"
      }
    },
    {
      "osm_id": 2699878589,
      "osm_type": "node",
      "name": "Unclassified mapped object",
      "raw_name": "Unnamed object",
      "feature_type": "other",
      "evidence_strength": "weak",
      "weight": 0.0,
      "distance_m": 47.1,
      "lat": 45.336257,
      "lon": 36.464559,
      "tags": {}
    },
    {
      "osm_id": 2699878582,
      "osm_type": "node",
      "name": "Unclassified mapped object",
      "raw_name": "Unnamed object",
      "feature_type": "other",
      "evidence_strength": "weak",
      "weight": 0.0,
      "distance_m": 47.3,
      "lat": 45.336156,
      "lon": 36.464718,
      "tags": {}
    },
    {
      "osm_id": 6486297606,
      "osm_type": "node",
      "name": "Unclassified mapped object",
      "raw_name": "Unnamed object",
      "feature_type": "other",
      "evidence_strength": "weak",
      "weight": 0.0,
      "distance_m": 51.8,
      "lat": 45.336865,
      "lon": 36.465477,
      "tags": {}
    },
    {
      "osm_id": 2699878617,
      "osm_type": "node",
      "name": "Unclassified mapped object",
      "raw_name": "Unnamed object",
      "feature_type": "other",
      "evidence_strength": "weak",
      "weight": 0.0,
      "distance_m": 52.6,
      "lat": 45.33699,
      "lon": 36.465116,
      "tags": {}
    },
    {
      "osm_id": 2699878618,
      "osm_type": "node",
      "name": "Unclassified mapped object",
      "raw_name": "Unnamed object",
      "feature_type": "other",
      "evidence_strength": "weak",
      "weight": 0.0,
      "distance_m": 52.6,
      "lat": 45.336993,
      "lon": 36.465088,
      "tags": {}
    },
    {
      "osm_id": 2699878616,
      "osm_type": "node",
      "name": "Unclassified mapped object",
      "raw_name": "Unnamed object",
      "feature_type": "other",
      "evidence_strength": "weak",
      "weight": 0.0,
      "distance_m": 52.7,
      "lat": 45.336988,
      "lon": 36.465149,
      "tags": {}
    },
    {
      "osm_id": 2699878583,
      "osm_type": "node",
      "name": "Unclassified mapped object",
      "raw_name": "Unnamed object",
      "feature_type": "other",
      "evidence_strength": "weak",
      "weight": 0.0,
      "distance_m": 54.6,
      "lat": 45.336165,
      "lon": 36.464549,
      "tags": {}
    },
    {
      "osm_id": 2699878619,
      "osm_type": "node",
      "name": "Unclassified mapped object",
      "raw_name": "Unnamed object",
      "feature_type": "other",
      "evidence_strength": "weak",
      "weight": 0.0,
      "distance_m": 56.9,
      "lat": 45.337026,
      "lon": 36.465155,
      "tags": {}
    },
    {
      "osm_id": 2699878620,
      "osm_type": "node",
      "name": "Unclassified mapped object",
      "raw_name": "Unnamed object",
      "feature_type": "other",
      "evidence_strength": "weak",
      "weight": 0.0,
      "distance_m": 56.9,
      "lat": 45.337028,
      "lon": 36.465123,
      "tags": {}
    },
    {
      "osm_id": 2699878621,
      "osm_type": "node",
      "name": "Unclassified mapped object",
      "raw_name": "Unnamed object",
      "feature_type": "other",
      "evidence_strength": "weak",
      "weight": 0.0,
      "distance_m": 56.9,
      "lat": 45.33703,
      "lon": 36.465094,
      "tags": {}
    }
  ],
  "nearby_features": [
    {
      "osm_id": 28006961,
      "osm_type": "node",
      "name": "Unclassified mapped object",
      "raw_name": "Unnamed object",
      "feature_type": "other",
      "evidence_strength": "weak",
      "weight": 0.0,
      "distance_m": 7.7,
      "lat": 45.33659,
      "lon": 36.465045,
      "tags": {}
    },
    {
      "osm_id": 9725199825,
      "osm_type": "node",
      "name": "Unclassified mapped object",
      "raw_name": "Unnamed object",
      "feature_type": "other",
      "evidence_strength": "weak",
      "weight": 0.0,
      "distance_m": 11.6,
      "lat": 45.33652,
      "lon": 36.464881,
      "tags": {}
    },
    {
      "osm_id": 9725199826,
      "osm_type": "node",
      "name": "Unclassified mapped object",
      "raw_name": "Unnamed object",
      "feature_type": "other",
      "evidence_strength": "weak",
      "weight": 0.0,
      "distance_m": 19.9,
      "lat": 45.336543,
      "lon": 36.464778,
      "tags": {}
    },
    {
      "osm_id": 2468736928,
      "osm_type": "node",
      "name": "Unclassified mapped object",
      "raw_name": "Unnamed object",
      "feature_type": "other",
      "evidence_strength": "weak",
      "weight": 0.0,
      "distance_m": 29.4,
      "lat": 45.336774,
      "lon": 36.465141,
      "tags": {}
    },
    {
      "osm_id": 9725199215,
      "osm_type": "node",
      "name": "Unclassified mapped object",
      "raw_name": "Unnamed object",
      "feature_type": "other",
      "evidence_strength": "weak",
      "weight": 0.0,
      "distance_m": 29.7,
      "lat": 45.336787,
      "lon": 36.465058,
      "tags": {}
    },
    {
      "osm_id": 9725199216,
      "osm_type": "node",
      "name": "Unclassified mapped object",
      "raw_name": "Unnamed object",
      "feature_type": "other",
      "evidence_strength": "weak",
      "weight": 0.0,
      "distance_m": 31.2,
      "lat": 45.336775,
      "lon": 36.465198,
      "tags": {}
    },
    {
      "osm_id": 5512201571,
      "osm_type": "node",
      "name": "Unclassified mapped object",
      "raw_name": "Unnamed object",
      "feature_type": "other",
      "evidence_strength": "weak",
      "weight": 0.0,
      "distance_m": 32.3,
      "lat": 45.336618,
      "lon": 36.464641,
      "tags": {}
    },
    {
      "osm_id": 2468736926,
      "osm_type": "node",
      "name": "Unclassified mapped object",
      "raw_name": "Unnamed object",
      "feature_type": "other",
      "evidence_strength": "weak",
      "weight": 0.0,
      "distance_m": 34.3,
      "lat": 45.336789,
      "lon": 36.465246,
      "tags": {}
    },
    {
      "osm_id": 1879085566,
      "osm_type": "node",
      "name": "Unclassified mapped object",
      "raw_name": "Unnamed object",
      "feature_type": "other",
      "evidence_strength": "weak",
      "weight": 0.0,
      "distance_m": 36.6,
      "lat": 45.336848,
      "lon": 36.465082,
      "tags": {}
    },
    {
      "osm_id": 2699878611,
      "osm_type": "node",
      "name": "Unclassified mapped object",
      "raw_name": "Unnamed object",
      "feature_type": "other",
      "evidence_strength": "weak",
      "weight": 0.0,
      "distance_m": 36.6,
      "lat": 45.336846,
      "lon": 36.465103,
      "tags": {}
    },
    {
      "osm_id": 2699878588,
      "osm_type": "node",
      "name": "Unclassified mapped object",
      "raw_name": "Unnamed object",
      "feature_type": "other",
      "evidence_strength": "weak",
      "weight": 0.0,
      "distance_m": 38.5,
      "lat": 45.336248,
      "lon": 36.464727,
      "tags": {}
    },
    {
      "osm_id": 2699878596,
      "osm_type": "node",
      "name": "Unclassified mapped object",
      "raw_name": "Unnamed object",
      "feature_type": "other",
      "evidence_strength": "weak",
      "weight": 0.0,
      "distance_m": 43.1,
      "lat": 45.336384,
      "lon": 36.464515,
      "tags": {}
    },
    {
      "osm_id": 1879085565,
      "osm_type": "node",
      "name": "Unclassified mapped object",
      "raw_name": "Unnamed object",
      "feature_type": "other",
      "evidence_strength": "weak",
      "weight": 0.0,
      "distance_m": 43.8,
      "lat": 45.336409,
      "lon": 36.464493,
      "tags": {}
    },
    {
      "osm_id": 264298404,
      "osm_type": "way",
      "name": "Pier / berth",
      "raw_name": "Unnamed object",
      "feature_type": "port",
      "evidence_strength": "strong",
      "weight": 11.2,
      "distance_m": 44.6,
      "lat": 45.336919,
      "lon": 36.465109,
      "tags": {
        "man_made": "pier"
      }
    },
    {
      "osm_id": 27933627,
      "osm_type": "node",
      "name": "Unclassified mapped object",
      "raw_name": "Unnamed object",
      "feature_type": "other",
      "evidence_strength": "weak",
      "weight": 0.0,
      "distance_m": 45.5,
      "lat": 45.336823,
      "lon": 36.465424,
      "tags": {}
    },
    {
      "osm_id": 264298335,
      "osm_type": "way",
      "name": "Unclassified mapped object",
      "raw_name": "Unnamed object",
      "feature_type": "other",
      "evidence_strength": "weak",
      "weight": 0.0,
      "distance_m": 46.5,
      "lat": 45.336206,
      "lon": 36.464638,
      "tags": {
        "building": "yes"
      }
    },
    {
      "osm_id": 2699878589,
      "osm_type": "node",
      "name": "Unclassified mapped object",
      "raw_name": "Unnamed object",
      "feature_type": "other",
      "evidence_strength": "weak",
      "weight": 0.0,
      "distance_m": 47.1,
      "lat": 45.336257,
      "lon": 36.464559,
      "tags": {}
    },
    {
      "osm_id": 2699878582,
      "osm_type": "node",
      "name": "Unclassified mapped object",
      "raw_name": "Unnamed object",
      "feature_type": "other",
      "evidence_strength": "weak",
      "weight": 0.0,
      "distance_m": 47.3,
      "lat": 45.336156,
      "lon": 36.464718,
      "tags": {}
    },
    {
      "osm_id": 6486297606,
      "osm_type": "node",
      "name": "Unclassified mapped object",
      "raw_name": "Unnamed object",
      "feature_type": "other",
      "evidence_strength": "weak",
      "weight": 0.0,
      "distance_m": 51.8,
      "lat": 45.336865,
      "lon": 36.465477,
      "tags": {}
    },
    {
      "osm_id": 2699878617,
      "osm_type": "node",
      "name": "Unclassified mapped object",
      "raw_name": "Unnamed object",
      "feature_type": "other",
      "evidence_strength": "weak",
      "weight": 0.0,
      "distance_m": 52.6,
      "lat": 45.33699,
      "lon": 36.465116,
      "tags": {}
    },
    {
      "osm_id": 2699878618,
      "osm_type": "node",
      "name": "Unclassified mapped object",
      "raw_name": "Unnamed object",
      "feature_type": "other",
      "evidence_strength": "weak",
      "weight": 0.0,
      "distance_m": 52.6,
      "lat": 45.336993,
      "lon": 36.465088,
      "tags": {}
    },
    {
      "osm_id": 2699878616,
      "osm_type": "node",
      "name": "Unclassified mapped object",
      "raw_name": "Unnamed object",
      "feature_type": "other",
      "evidence_strength": "weak",
      "weight": 0.0,
      "distance_m": 52.7,
      "lat": 45.336988,
      "lon": 36.465149,
      "tags": {}
    },
    {
      "osm_id": 2699878583,
      "osm_type": "node",
      "name": "Unclassified mapped object",
      "raw_name": "Unnamed object",
      "feature_type": "other",
      "evidence_strength": "weak",
      "weight": 0.0,
      "distance_m": 54.6,
      "lat": 45.336165,
      "lon": 36.464549,
      "tags": {}
    },
    {
      "osm_id": 264298423,
      "osm_type": "way",
      "name": "Pier / berth",
      "raw_name": "Unnamed object",
      "feature_type": "port",
      "evidence_strength": "strong",
      "weight": 11.2,
      "distance_m": 54.8,
      "lat": 45.337009,
      "lon": 36.465122,
      "tags": {
        "man_made": "pier"
      }
    },
    {
      "osm_id": 2699878619,
      "osm_type": "node",
      "name": "Unclassified mapped object",
      "raw_name": "Unnamed object",
      "feature_type": "other",
      "evidence_strength": "weak",
      "weight": 0.0,
      "distance_m": 56.9,
      "lat": 45.337026,
      "lon": 36.465155,
      "tags": {}
    }
  ],
  "assessment": "The selected coordinate is assessed as port-linked energy / refinery infrastructure with HIGH confidence. The primary mapped object is port infrastructure with HIGH confidence. The surrounding operational environment is rail logistics area with HIGH confidence. The nearest settlement context is Керчь, Автономна Республіка Крим, Україна. Wikidata nearest candidate is Kerch. Railway intelligence confirms nearby rail-related infrastructure with HIGH confidence. Maritime intelligence identifies port with rail-connected logistics infrastructure with HIGH confidence. No FIRMS thermal anomaly is detected within the selected radius in the available local FIRMS windows. This is a rule-based multi-source OSINT assessment and should be verified by satellite imagery.",
  "job": {
    "id": "ci_20260630_122241",
    "type": "coordinate_intelligence",
    "created_at": "2026-06-30T12:22:41.742254+00:00",
    "processed_at": "2026-06-30T12:22:51.080723+00:00",
    "source": "manual_map_request",
    "radius": 750
  }
}