{
  "date": "2026-06-02",
  "updated_utc": "2026-06-02T11:50:20.784140+00:00",
  "front_activity_index": 63,
  "status": "HIGH",
  "components": {
    "osint_density": 25,
    "firms_activity": 20,
    "territorial_change": 0.0,
    "active_sectors": 10,
    "critical_events": 8
  },
  "counts": {
    "osint": 21,
    "firms_3d": 191,
    "firms_10d": 1354,
    "firms_30d": 13703,
    "critical_events": 4,
    "active_sectors": 6
  },
  "territorial": {
    "available": true,
    "error": null,
    "previous_file": "deepstatemap_data_20260601.geojson",
    "current_file": "deepstatemap_data_20260602.geojson",
    "previous_total_km2": 116586.05,
    "current_total_km2": 116586.05,
    "russian_gain_km2": 0,
    "ukrainian_recapture_km2": 0,
    "net_change_km2": 0.0,
    "method": "Approximate total area difference between latest two DeepState GeoJSON files"
  },
  "territorial_hotspot": {
    "sector": "Pokrovsk",
    "lat": 48.28,
    "lon": 37.18,
    "zoom": 9,
    "score": 85,
    "change_km2": 0.0,
    "method": "Top classified sector based on OSINT + FIRMS density"
  },
  "top_sectors": [
    {
      "sector": "Other / Unclassified",
      "osint": 9,
      "firms": 145,
      "score": 100
    },
    {
      "sector": "Pokrovsk",
      "osint": 7,
      "firms": 1,
      "score": 85
    },
    {
      "sector": "Crimea",
      "osint": 4,
      "firms": 7,
      "score": 54
    },
    {
      "sector": "Kharkiv",
      "osint": 1,
      "firms": 11,
      "score": 22
    },
    {
      "sector": "Zaporizhzhia",
      "osint": 0,
      "firms": 22,
      "score": 20
    },
    {
      "sector": "Kherson-Dnipro",
      "osint": 0,
      "firms": 3,
      "score": 3
    },
    {
      "sector": "Lyman",
      "osint": 0,
      "firms": 2,
      "score": 2
    },
    {
      "sector": "Kupiansk",
      "osint": 0,
      "firms": 0,
      "score": 0
    }
  ],
  "top_events": [
    {
      "title": "Reported military-related update near Krím",
      "source": "forrás nélkül",
      "sector": "Crimea"
    },
    {
      "title": "Reported rear-area strike near Krím",
      "source": "forrás nélkül",
      "sector": "Crimea"
    },
    {
      "title": "Reported drone strike near Harkiv",
      "source": "forrás nélkül",
      "sector": "Kharkiv"
    },
    {
      "title": "Reported drone strike near Krím",
      "source": "forrás nélkül",
      "sector": "Crimea"
    },
    {
      "title": "Reported rear-area strike near Volgográd",
      "source": "forrás nélkül",
      "sector": "Other / Unclassified"
    },
    {
      "title": "Reported rear-area strike near Krasznodar",
      "source": "forrás nélkül",
      "sector": "Other / Unclassified"
    }
  ],
  "data_sources": {
    "osint": "data/osint_feed.json",
    "firms_3d": "data/firms_3.json",
    "firms_10d": "data/firms_10.json",
    "firms_30d": "data/firms_30.json",
    "deepstate": "cyterat/deepstate-map-data via GitHub API"
  },
  "note": "Front Activity Index: nem hivatalos katonai mutató, blogos vizuális támogatásra."
}